{"access_token": "ya29.GlwBBGUOKtbeFrfelmVn9dkHwl5uoFenx3o7fNNguUCGtZqi1WL5bmEFD0tbrYgocY09nmP_hFZS4Qlt9mlxch5xYtFIjrBen-aC1ZXTQE-y_jbSIMgbCtrPCPV0nQ", "client_id": "927321190727-renbq00un4jp9u10f1gaehcjglns34r4.apps.googleusercontent.com", "client_secret": "uFJsuFP0UnediAKYmyS3HmGx", "refresh_token": "1/ZOGO8z52V5SV9E-D0V3edm9HblE9udi5C6jxBd6Yzy8", "token_expiry": "2017-03-01T10:19:55Z", "token_uri": "https://accounts.google.com/o/oauth2/token", "user_agent": "GooGIS plugin", "revoke_uri": "https://accounts.google.com/o/oauth2/revoke", "id_token": null, "id_token_jwt": null, "token_response": {"access_token": "ya29.GlwBBGUOKtbeFrfelmVn9dkHwl5uoFenx3o7fNNguUCGtZqi1WL5bmEFD0tbrYgocY09nmP_hFZS4Qlt9mlxch5xYtFIjrBen-aC1ZXTQE-y_jbSIMgbCtrPCPV0nQ", "expires_in": 3600, "token_type": "Bearer"}, "scopes": ["https://www.googleapis.com/auth/spreadsheets.readonly", "https://www.googleapis.com/auth/drive.readonly", "https://www.googleapis.com/auth/spreadsheets", "https://www.googleapis.com/auth/drive"], "token_info_uri": "https://www.googleapis.com/oauth2/v3/tokeninfo", "invalid": false, "_class": "OAuth2Credentials", "_module": "oauth2client.client"}